SVcode/extend/extend.sv
module extend (
    input  logic [31:0] Instr,      // Full 32-bit instruction
    input  logic [2:0]  ImmSrc,     // Immediate type selector
    output logic [31:0] ImmExt      // Extended immediate
);

always_comb begin
    case (ImmSrc)
        3'b000: begin
            // I-type immediate
            ImmExt = {{20{Instr[31]}}, Instr[31:20]};
        end

        3'b001: begin
            // S-type immediate
            ImmExt = {{20{Instr[31]}}, Instr[31:25], Instr[11:7]};
        end

        3'b010: begin
            // B-type immediate
            ImmExt = {{19{Instr[31]}}, Instr[31], Instr[7], Instr[30:25], Instr[11:8], 1'b0};
        end

        3'b011: begin
            // U-type immediate
            ImmExt = {Instr[31:12], 12'b0};
        end

        3'b100: begin
            // J-type immediate
            ImmExt = {{12{Instr[31]}}, Instr[19:12], Instr[20], Instr[30:21], 1'b0};
        end

        default: begin
            ImmExt = 32'h00000000;
        end

    endcase
end

endmodule

SVcode/extend/extend_tb.sv
`timescale 1ns/1ps
`include "./SVcode/extend/extend.sv"

module extend_tb;

    logic [31:0] Instr;
    logic [2:0]  ImmSrc;
    logic [31:0] ImmExt;

    extend dut (
        .Instr(Instr),
        .ImmSrc(ImmSrc),
        .ImmExt(ImmExt)
    );

    initial begin
        $dumpfile("extend_tb.vcd");
        $dumpvars(0, extend_tb);
    end

    initial begin
        $display("Time\tImmSrc\tInstr\t\t\tImmExt");
        $monitor("%0t\t%b\t%h\t%h", $time, ImmSrc, Instr, ImmExt);

        // I-type immediate tests
        Instr  = 32'h00500093;   // imm = 5
        ImmSrc = 3'b000;
        #10;

        Instr  = 32'h00C00113;   // imm = 12
        ImmSrc = 3'b000;
        #10;

        Instr  = 32'hFFF00093;   // imm = -1
        ImmSrc = 3'b000;
        #10;

        Instr  = 32'h80000093;   // imm = -2048
        ImmSrc = 3'b000;
        #10;

        // S-type immediate tests
        Instr  = 32'h0020A423;   // imm = 8
        ImmSrc = 3'b001;
        #10;

        Instr  = 32'hFE20AE23;   // imm = -4
        ImmSrc = 3'b001;
        #10;

        Instr  = 32'h7E20AF23;   // positive S-type immediate
        ImmSrc = 3'b001;
        #10;

        // B-type immediate tests
        Instr  = 32'h00208863;   // imm = 16
        ImmSrc = 3'b010;
        #10;

        Instr  = 32'hFE208EE3;   // negative branch immediate
        ImmSrc = 3'b010;
        #10;

        Instr  = 32'h00000063;   // imm = 0
        ImmSrc = 3'b010;
        #10;

        Instr  = 32'h7E208FE3;   // positive branch immediate
        ImmSrc = 3'b010;
        #10;

        // U-type immediate tests
        Instr  = 32'h123450B7;   // imm = 0x12345000
        ImmSrc = 3'b011;
        #10;

        Instr  = 32'hABCDE137;   // imm = 0xABCDE000
        ImmSrc = 3'b011;
        #10;

        Instr  = 32'hFFF00037;   // imm = 0xFFF00000
        ImmSrc = 3'b011;
        #10;

        // J-type immediate tests
        Instr  = 32'h001000EF;   // small positive jump immediate
        ImmSrc = 3'b100;
        #10;

        Instr  = 32'h7FF000EF;   // large positive jump immediate
        ImmSrc = 3'b100;
        #10;

        Instr  = 32'h800000EF;   // negative jump immediate
        ImmSrc = 3'b100;
        #10;

        Instr  = 32'h000000EF;   // imm = 0
        ImmSrc = 3'b100;
        #10;

        $finish;
    end

endmodule

SVcode/extend/extend_tb.vcd
$date
	Sun Mar 29 07:44:45 2026
$end
$version
	Icarus Verilog
$end
$timescale
	1ps
$end
$scope module extend_tb $end
$var wire 32 ! ImmExt [31:0] $end
$var reg 3 " ImmSrc [2:0] $end
$var reg 32 # Instr [31:0] $end
$scope module dut $end
$var wire 3 $ ImmSrc [2:0] $end
$var wire 32 % Instr [31:0] $end
$var reg 32 & ImmExt [31:0] $end
$upscope $end
$upscope $end
$enddefinitions $end
#0
$dumpvars
b101 &
b10100000000000010010011 %
b0 $
b10100000000000010010011 #
b0 "
b101 !
$end
#10000
b1100 !
b1100 &
b110000000000000100010011 #
b110000000000000100010011 %
#20000
b11111111111111111111111111111111 !
b11111111111111111111111111111111 &
b11111111111100000000000010010011 #
b11111111111100000000000010010011 %
#30000
b11111111111111111111100000000000 !
b11111111111111111111100000000000 &
b10000000000000000000000010010011 #
b10000000000000000000000010010011 %
#40000
b1000 !
b1000 &
b1 "
b1 $
b1000001010010000100011 #
b1000001010010000100011 %
#50000
b11111111111111111111111111111100 !
b11111111111111111111111111111100 &
b11111110001000001010111000100011 #
b11111110001000001010111000100011 %
#60000
b11111111110 !
b11111111110 &
b1111110001000001010111100100011 #
b1111110001000001010111100100011 %
#70000
b10000 !
b10000 &
b10 "
b10 $
b1000001000100001100011 #
b1000001000100001100011 %
#80000
b11111111111111111111111111111100 !
b11111111111111111111111111111100 &
b11111110001000001000111011100011 #
b11111110001000001000111011100011 %
#90000
b0 !
b0 &
b1100011 #
b1100011 %
#100000
b111111111110 !
b111111111110 &
b1111110001000001000111111100011 #
b1111110001000001000111111100011 %
#110000
b10010001101000101000000000000 !
b10010001101000101000000000000 &
b11 "
b11 $
b10010001101000101000010110111 #
b10010001101000101000010110111 %
#120000
b10101011110011011110000000000000 !
b10101011110011011110000000000000 &
b10101011110011011110000100110111 #
b10101011110011011110000100110111 %
#130000
b11111111111100000000000000000000 !
b11111111111100000000000000000000 &
b11111111111100000000000000110111 #
b11111111111100000000000000110111 %
#140000
b100000000000 !
b100000000000 &
b100 "
b100 $
b100000000000011101111 #
b100000000000011101111 %
#150000
b111111111110 !
b111111111110 &
b1111111111100000000000011101111 #
b1111111111100000000000011101111 %
#160000
b11111111111100000000000000000000 !
b11111111111100000000000000000000 &
b10000000000000000000000011101111 #
b10000000000000000000000011101111 %
#170000
b0 !
b0 &
b11101111 #
b11101111 %
