SVcode/control_unit/control_unit.sv
module control_unit (
    input  logic [31:0] instr,
    input  logic        Zero,

    output logic        RegWrite,
    output logic [2:0]  ImmSrc,
    output logic        ALUSrc,
    output logic [4:0]  ALUControl,
    output logic        MemWrite,
    output logic [1:0]  ResultSrc,
    output logic [1:0]  PCSrc
);

    logic [6:0] opcode;
    logic [2:0] funct3;
    logic [6:0] funct7;

    assign opcode = instr[6:0];
    assign funct3 = instr[14:12];
    assign funct7 = instr[31:25];

    always_comb begin
        // default values
        RegWrite   = 1'b0;
        ImmSrc     = 3'b000;
        ALUSrc     = 1'b0;
        ALUControl = 5'b00000;
        MemWrite   = 1'b0;
        ResultSrc  = 2'b00;
        PCSrc      = 2'b00;

        case (opcode)

            // =========================
            // R-type: add, sub, or, and, sll, srl, slt
            // opcode = 0110011
            // =========================
            7'b0110011: begin
                RegWrite  = 1'b1;
                ALUSrc    = 1'b0;
                ResultSrc = 2'b01;
                PCSrc     = 2'b00;

                case (funct3)
                    3'b000: begin
                        if (funct7 == 7'b0100000)
                            ALUControl = 5'b01010; // sub
                        else
                            ALUControl = 5'b00010; // add
                    end
                    3'b110: ALUControl = 5'b00111; // or
                    3'b111: ALUControl = 5'b00011; // and
                    3'b001: ALUControl = 5'b00000; // sll
                    3'b101: ALUControl = 5'b10000; // srl
                    3'b010: ALUControl = 5'b01001; // slt
                    default: ALUControl = 5'b00000;
                endcase
            end

            // =========================
            // I-type arithmetic:
            // addi, ori, andi, slli, srli, slti
            // opcode = 0010011
            // =========================
            7'b0010011: begin
                RegWrite  = 1'b1;
                ImmSrc    = 3'b000;
                ALUSrc    = 1'b1;
                ResultSrc = 2'b01;
                PCSrc     = 2'b00;

                case (funct3)
                    3'b000: ALUControl = 5'b00010; // addi
                    3'b110: ALUControl = 5'b00111; // ori
                    3'b111: ALUControl = 5'b00011; // andi
                    3'b001: ALUControl = 5'b00000; // slli
                    3'b101: ALUControl = 5'b10000; // srli
                    3'b010: ALUControl = 5'b01001; // slti
                    default: ALUControl = 5'b00000;
                endcase
            end

            // =========================
            // lw
            // opcode = 0000011
            // =========================
            7'b0000011: begin
                RegWrite   = 1'b1;
                ImmSrc     = 3'b000;
                ALUSrc     = 1'b1;
                ALUControl = 5'b00010; // add for address
                MemWrite   = 1'b0;
                ResultSrc  = 2'b10;
                PCSrc      = 2'b00;
            end

            // =========================
            // sw
            // opcode = 0100011
            // =========================
            7'b0100011: begin
                RegWrite   = 1'b0;
                ImmSrc     = 3'b001;
                ALUSrc     = 1'b1;
                ALUControl = 5'b00010; // add for address
                MemWrite   = 1'b1;
                ResultSrc  = 2'b00;    // don't care
                PCSrc      = 2'b00;
            end

            // =========================
            // Branches: beq, bne, blt, bge
            // opcode = 1100011
            // =========================
            7'b1100011: begin
                RegWrite  = 1'b0;
                ImmSrc    = 3'b010;
                ALUSrc    = 1'b0;
                MemWrite  = 1'b0;
                ResultSrc = 2'b00; // don't care

                case (funct3)
                    3'b000: begin
                        ALUControl = 5'b01010;           // beq -> sub
                        PCSrc      = Zero ? 2'b01 : 2'b00;
                    end
                    3'b001: begin
                        ALUControl = 5'b01010;           // bne -> sub
                        PCSrc      = Zero ? 2'b00 : 2'b01;
                    end
                    3'b100: begin
                        ALUControl = 5'b01001;           // blt -> slt
                        PCSrc      = Zero ? 2'b00 : 2'b01;
                    end
                    3'b101: begin
                        ALUControl = 5'b01001;           // bge -> slt
                        PCSrc      = Zero ? 2'b01 : 2'b00;
                    end
                    default: begin
                        ALUControl = 5'b00010;
                        PCSrc      = 2'b00;
                    end
                endcase
            end

            // =========================
            // jal
            // opcode = 1101111
            // =========================
            7'b1101111: begin
                RegWrite   = 1'b1;
                ImmSrc     = 3'b100;
                ALUSrc     = 1'b0;      // don't care
                ALUControl = 5'b00000;  // don't care
                MemWrite   = 1'b0;
                ResultSrc  = 2'b11;     // write PC+4
                PCSrc      = 2'b01;
            end

            // =========================
            // jalr
            // opcode = 1100111
            // =========================
            7'b1100111: begin
                RegWrite   = 1'b1;
                ImmSrc     = 3'b000;
                ALUSrc     = 1'b1;
                ALUControl = 5'b00010;  // rs1 + imm
                MemWrite   = 1'b0;
                ResultSrc  = 2'b11;     // write PC+4
                PCSrc      = 2'b10;
            end

            // =========================
            // lui
            // opcode = 0110111
            // =========================
            7'b0110111: begin
                RegWrite   = 1'b1;
                ImmSrc     = 3'b011;
                ALUSrc     = 1'b0;      // don't care
                ALUControl = 5'b00000;  // don't care
                MemWrite   = 1'b0;
                ResultSrc  = 2'b00;     // immediate
                PCSrc      = 2'b00;
            end

            default: begin
                RegWrite   = 1'b0;
                ImmSrc     = 3'b000;
                ALUSrc     = 1'b0;
                ALUControl = 5'b00000;
                MemWrite   = 1'b0;
                ResultSrc  = 2'b00;
                PCSrc      = 2'b00;
            end
        endcase
    end

endmodule

SVcode/control_unit/control_unit_tb.sv
`timescale 1ns/1ps
`include "./SVcode/control_unit/control_unit.sv"

module control_unit_tb;

    logic [31:0] instr;
    logic        Zero;

    logic        RegWrite;
    logic [2:0]  ImmSrc;
    logic        ALUSrc;
    logic [4:0]  ALUControl;
    logic        MemWrite;
    logic [1:0]  ResultSrc;
    logic [1:0]  PCSrc;

    control_unit dut (
        .instr(instr),
        .Zero(Zero),
        .RegWrite(RegWrite),
        .ImmSrc(ImmSrc),
        .ALUSrc(ALUSrc),
        .ALUControl(ALUControl),
        .MemWrite(MemWrite),
        .ResultSrc(ResultSrc),
        .PCSrc(PCSrc)
    );

    initial begin
        $dumpfile("control_unit_tb.vcd");
        $dumpvars(0, control_unit_tb);
    end

    initial begin
        $display("Time\tinstr\t\t\tZero\tRegWrite ImmSrc ALUSrc ALUCtrl MemWrite ResultSrc PCSrc");
        $monitor("%0t\t%h\t%b\t%b\t %b\t   %b\t   %b\t   %b\t    %b\t    %b",
                 $time, instr, Zero, RegWrite, ImmSrc, ALUSrc, ALUControl,
                 MemWrite, ResultSrc, PCSrc);

        // =========================================================
        // R-type instruction tests
        // =========================================================

        // add  x1, x2, x3
        instr = 32'b0000000_00011_00010_000_00001_0110011; Zero = 0;
        #10;

        // sub  x1, x2, x3
        instr = 32'b0100000_00011_00010_000_00001_0110011; Zero = 0;
        #10;

        // or   x1, x2, x3
        instr = 32'b0000000_00011_00010_110_00001_0110011; Zero = 0;
        #10;

        // and  x1, x2, x3
        instr = 32'b0000000_00011_00010_111_00001_0110011; Zero = 0;
        #10;

        // sll  x1, x2, x3
        instr = 32'b0000000_00011_00010_001_00001_0110011; Zero = 0;
        #10;

        // srl  x1, x2, x3
        instr = 32'b0000000_00011_00010_101_00001_0110011; Zero = 0;
        #10;

        // slt  x1, x2, x3
        instr = 32'b0000000_00011_00010_010_00001_0110011; Zero = 0;
        #10;

        // =========================================================
        // I-type arithmetic instruction tests
        // =========================================================

        // addi x1, x2, 5
        instr = 32'b000000000101_00010_000_00001_0010011; Zero = 0;
        #10;

        // ori  x1, x2, 5
        instr = 32'b000000000101_00010_110_00001_0010011; Zero = 0;
        #10;

        // andi x1, x2, 5
        instr = 32'b000000000101_00010_111_00001_0010011; Zero = 0;
        #10;

        // slli x1, x2, 3
        instr = 32'b0000000_00011_00010_001_00001_0010011; Zero = 0;
        #10;

        // srli x1, x2, 3
        instr = 32'b0000000_00011_00010_101_00001_0010011; Zero = 0;
        #10;

        // slti x1, x2, 5
        instr = 32'b000000000101_00010_010_00001_0010011; Zero = 0;
        #10;

        // =========================================================
        // Memory access instruction tests
        // =========================================================

        // lw x1, 8(x2)
        instr = 32'b000000001000_00010_010_00001_0000011; Zero = 0;
        #10;

        // sw x3, 8(x2)
        instr = 32'b0000000_00011_00010_010_01000_0100011; Zero = 0;
        #10;

        // =========================================================
        // Branch instruction tests
        // =========================================================

        // beq taken
        instr = 32'b0000000_00011_00010_000_01000_1100011; Zero = 1;
        #10;

        // beq not taken
        instr = 32'b0000000_00011_00010_000_01000_1100011; Zero = 0;
        #10;

        // bne taken
        instr = 32'b0000000_00011_00010_001_01000_1100011; Zero = 0;
        #10;

        // bne not taken
        instr = 32'b0000000_00011_00010_001_01000_1100011; Zero = 1;
        #10;

        // blt taken (using slt + ~Zero)
        instr = 32'b0000000_00011_00010_100_01000_1100011; Zero = 0;
        #10;

        // blt not taken
        instr = 32'b0000000_00011_00010_100_01000_1100011; Zero = 1;
        #10;

        // bge taken (using slt + Zero)
        instr = 32'b0000000_00011_00010_101_01000_1100011; Zero = 1;
        #10;

        // bge not taken
        instr = 32'b0000000_00011_00010_101_01000_1100011; Zero = 0;
        #10;

        // =========================================================
        // Jump instruction tests
        // =========================================================

        // jal x1, offset
        instr = 32'b0_0000001010_1_00000000_00001_1101111; Zero = 0;
        #10;

        // jalr x1, x2, 4
        instr = 32'b000000000100_00010_000_00001_1100111; Zero = 0;
        #10;

        // =========================================================
        // U-type instruction test
        // =========================================================

        // lui x1, 0x12345
        instr = 32'b00010010001101000101_00001_0110111; Zero = 0;
        #10;

        $finish;
    end

endmodule

SVcode/control_unit/control_unit_tb.vcd
$date
	Thu Mar 26 05:25:24 2026
$end
$version
	Icarus Verilog
$end
$timescale
	1ps
$end
$scope module control_unit_tb $end
$var wire 2 ! ResultSrc [1:0] $end
$var wire 1 " RegWrite $end
$var wire 2 # PCSrc [1:0] $end
$var wire 1 $ MemWrite $end
$var wire 3 % ImmSrc [2:0] $end
$var wire 1 & ALUSrc $end
$var wire 5 ' ALUControl [4:0] $end
$var reg 1 ( Zero $end
$var reg 32 ) instr [31:0] $end
$scope module dut $end
$var wire 1 ( Zero $end
$var wire 32 * instr [31:0] $end
$var wire 7 + opcode [6:0] $end
$var wire 7 , funct7 [6:0] $end
$var wire 3 - funct3 [2:0] $end
$var reg 5 . ALUControl [4:0] $end
$var reg 1 & ALUSrc $end
$var reg 3 / ImmSrc [2:0] $end
$var reg 1 $ MemWrite $end
$var reg 2 0 PCSrc [1:0] $end
$var reg 1 " RegWrite $end
$var reg 2 1 ResultSrc [1:0] $end
$upscope $end
$upscope $end
$enddefinitions $end
#0
$dumpvars
b1 1
b0 0
b0 /
b10 .
b0 -
b0 ,
b110011 +
b1100010000000010110011 *
b1100010000000010110011 )
0(
b10 '
0&
b0 %
0$
b0 #
1"
b1 !
$end
#10000
b1 !
b1 1
b1010 '
b1010 .
1"
b100000 ,
b1000000001100010000000010110011 )
b1000000001100010000000010110011 *
#20000
b1 !
b1 1
b111 '
b111 .
1"
b110 -
b0 ,
b1100010110000010110011 )
b1100010110000010110011 *
#30000
b1 !
b1 1
b11 '
b11 .
1"
b111 -
b1100010111000010110011 )
b1100010111000010110011 *
#40000
b1 !
b1 1
b0 '
b0 .
1"
b1 -
b1100010001000010110011 )
b1100010001000010110011 *
#50000
b10000 '
b10000 .
b1 !
b1 1
1"
b101 -
b1100010101000010110011 )
b1100010101000010110011 *
#60000
b1 !
b1 1
b1001 '
b1001 .
1"
b10 -
b1100010010000010110011 )
b1100010010000010110011 *
#70000
1&
b1 !
b1 1
b10 '
b10 .
1"
b10011 +
b0 -
b10100010000000010010011 )
b10100010000000010010011 *
#80000
b1 !
b1 1
b111 '
b111 .
1&
1"
b110 -
b10100010110000010010011 )
b10100010110000010010011 *
#90000
b1 !
b1 1
b11 '
b11 .
1&
1"
b111 -
b10100010111000010010011 )
b10100010111000010010011 *
#100000
b1 !
b1 1
b0 '
b0 .
1&
1"
b1 -
b1100010001000010010011 )
b1100010001000010010011 *
#110000
b10000 '
b10000 .
b1 !
b1 1
1&
1"
b101 -
b1100010101000010010011 )
b1100010101000010010011 *
#120000
b1 !
b1 1
b1001 '
b1001 .
1&
1"
b10 -
b10100010010000010010011 )
b10100010010000010010011 *
#130000
b10 !
b10 1
b10 '
b10 .
1&
1"
b11 +
b100000010010000010000011 )
b100000010010000010000011 *
#140000
1$
b1 %
b1 /
b0 !
b0 1
b10 '
b10 .
1&
0"
b100011 +
b1100010010010000100011 )
b1100010010010000100011 *
#150000
b1 #
b1 0
0$
b1010 '
b1010 .
0&
b10 %
b10 /
b1100011 +
b0 -
1(
b1100010000010001100011 )
b1100010000010001100011 *
#160000
b0 #
b0 0
b1010 '
b1010 .
b10 %
b10 /
0(
#170000
b1 #
b1 0
b1010 '
b1010 .
b10 %
b10 /
b1 -
b1100010001010001100011 )
b1100010001010001100011 *
#180000
b0 #
b0 0
b1010 '
b1010 .
b10 %
b10 /
1(
#190000
b1 #
b1 0
b1001 '
b1001 .
b10 %
b10 /
b100 -
0(
b1100010100010001100011 )
b1100010100010001100011 *
#200000
b0 #
b0 0
b1001 '
b1001 .
b10 %
b10 /
1(
#210000
b1 #
b1 0
b1001 '
b1001 .
b10 %
b10 /
b101 -
b1100010101010001100011 )
b1100010101010001100011 *
#220000
b0 #
b0 0
b1001 '
b1001 .
b10 %
b10 /
0(
#230000
b1 #
b1 0
b11 !
b11 1
1"
b0 '
b0 .
b100 %
b100 /
b1101111 +
b0 -
b1010100000000000011101111 )
b1010100000000000011101111 *
#240000
b10 '
b10 .
1&
b10 #
b10 0
b11 !
b11 1
b0 %
b0 /
1"
b1100111 +
b10000010000000011100111 )
b10000010000000011100111 *
#250000
b11 %
b11 /
b0 #
b0 0
b0 !
b0 1
b0 '
b0 .
0&
1"
b110111 +
b101 -
b1001 ,
b10010001101000101000010110111 )
b10010001101000101000010110111 *
