SVcode/pc/pc.sv
module program_counter (
    input  logic        CLK,
    input  logic        reset,
    input  logic [31:0] PCNext,
    output logic [31:0] PC
);

always_ff @(posedge CLK) begin
    if (reset)
        PC <= 32'h00000000;
    else
        PC <= PCNext;
end

endmodule

SVcode/pc/pc_tb.sv
`timescale 1ns/1ps
`include "./SVcode/pc/pc.sv"

module program_counter_tb;

    logic        CLK;
    logic        reset;
    logic [31:0] PCNext;
    logic [31:0] PC;

    program_counter dut (
        .CLK(CLK),
        .reset(reset),
        .PCNext(PCNext),
        .PC(PC)
    );

    initial begin
        $dumpfile("program_counter_tb.vcd");
        $dumpvars(0, program_counter_tb);
    end

    initial begin
        CLK = 0;
        forever #5 CLK = ~CLK;
    end

    initial begin
        $display("Time\tCLK\treset\tPCNext\t\tPC");

        $monitor("%0t\t%b\t%b\t%h\t%h", $time, CLK, reset, PCNext, PC);
        
        reset  = 1;
        PCNext = 32'h00000004;
        #10;

        reset  = 0;
        PCNext = 32'h00000004;
        #10;

        PCNext = 32'h00000008;
        #10;

        PCNext = 32'h0000000C;
        #10;

        reset = 1;
        PCNext = 32'h00000010;
        #10;

        reset = 0;
        PCNext = 32'h00000014;
        #10;

        $finish;
    end

endmodule

SVcode/pc/program_counter_tb.vcd
$date
	Sun Mar 29 07:44:45 2026
$end
$version
	Icarus Verilog
$end
$timescale
	1ps
$end
$scope module program_counter_tb $end
$var wire 32 ! PC [31:0] $end
$var reg 1 " CLK $end
$var reg 32 # PCNext [31:0] $end
$var reg 1 $ reset $end
$scope module dut $end
$var wire 1 " CLK $end
$var wire 32 % PCNext [31:0] $end
$var wire 1 $ reset $end
$var reg 32 & PC [31:0] $end
$upscope $end
$upscope $end
$enddefinitions $end
#0
$dumpvars
bx &
b100 %
1$
b100 #
0"
bx !
$end
#5000
b0 !
b0 &
1"
#10000
0"
0$
#15000
b100 !
b100 &
1"
#20000
0"
b1000 #
b1000 %
#25000
b1000 !
b1000 &
1"
#30000
0"
b1100 #
b1100 %
#35000
b1100 !
b1100 &
1"
#40000
0"
b10000 #
b10000 %
1$
#45000
b0 !
b0 &
1"
#50000
0"
b10100 #
b10100 %
0$
#55000
b10100 !
b10100 &
1"
