SVcode/alu/alu.sv
module alu (
    input  logic [31:0] A,             // ALU input A
    input  logic [31:0] B,             // ALU input B
    input  logic [4:0]  ALUControl,    // ALU control signal
    output logic [31:0] ALUResult,     // ALU output result
    output logic        Zero          // Zero flag
);

    logic [31:0] shift_result;
    logic [31:0] arith_result;
    logic [31:0] logic_result;
    logic [31:0] slt_result;


    always_comb begin
        
        // Shift path
        // ALUControl[4] = 0 for SLL, 1 for SRL
        case (ALUControl[4])
            1'b0: shift_result = A << B[4:0];
            1'b1: shift_result = A >> B[4:0];
        endcase

        // Arithmetic path
        // ALUControl[3] = 0 for add, 1 for subtract
        case (ALUControl[3])
            1'b0: arith_result = A + B;
            1'b1: arith_result = A - B;
        endcase

        // Logic path
        // ALUControl[2] = 0 for AND, 1 for OR
        case (ALUControl[2])
            1'b0: logic_result = A & B;
            1'b1: logic_result = A | B;
        endcase

        // Signed comparison must not rely only on the subtraction sign bit,
        // because subtraction can overflow when operands have different signs.
        slt_result = {31'b0, $signed(A) < $signed(B)};

        // Main ALU output multiplexer
        case (ALUControl[1:0])
            2'b00: ALUResult = shift_result;
            2'b01: ALUResult = slt_result;
            2'b10: ALUResult = arith_result;
            2'b11: ALUResult = logic_result;
            default: ALUResult = 32'h0;
        endcase
    end

    // Status flags
    assign Zero     = (ALUResult == 32'h0);

endmodule

SVcode/alu/alu_tb.sv
`timescale 1ns/1ps
`include "./SVcode/alu/alu.sv"

module alu_tb;

    logic [31:0] A;
    logic [31:0] B;
    logic [4:0]  ALUControl;
    logic [31:0] ALUResult;
    logic        Zero;

    alu dut (
        .A(A),
        .B(B),
        .ALUControl(ALUControl),
        .ALUResult(ALUResult),
        .Zero(Zero)
    );

    initial begin
        $dumpfile("alu_tb.vcd");
        $dumpvars(0, alu_tb);
    end

    initial begin
        $display("Time\tALUControl\tA\t\tB\t\tALUResult\tZero");
        $monitor("%0t\t%b\t\t%h\t%h\t%h\t%b",
                 $time, ALUControl, A, B, ALUResult, Zero);

        // =========================================================
        // Shift operation tests
        // ALUControl[1:0] = 00
        // ALUControl[4]   = 0 for SLL, 1 for SRL
        // =========================================================

        // SLL: 1 << 2 = 4
        A = 32'h00000001; B = 32'h00000002; ALUControl = 5'b00000;
        #10;

        // SLL: 3 << 4 = 0x30
        A = 32'h00000003; B = 32'h00000004; ALUControl = 5'b00000;
        #10;

        // SLL: shift by 0
        A = 32'h12345678; B = 32'h00000000; ALUControl = 5'b00000;
        #10;

        // SRL: 0x10 >> 2 = 0x4
        A = 32'h00000010; B = 32'h00000002; ALUControl = 5'b10000;
        #10;

        // SRL: 0x80000000 >> 4 = 0x08000000
        A = 32'h80000000; B = 32'h00000004; ALUControl = 5'b10000;
        #10;

        // SRL: shift by 0
        A = 32'h87654321; B = 32'h00000000; ALUControl = 5'b10000;
        #10;

        // =========================================================
        // SLT operation tests
        // ALUControl[1:0] = 01
        // Arithmetic path uses subtraction when ALUControl[3] = 1
        // =========================================================

        // 3 < 5 -> result should be 1
        A = 32'h00000003; B = 32'h00000005; ALUControl = 5'b01001;
        #10;

        // 7 < 2 -> result should be 0
        A = 32'h00000007; B = 32'h00000002; ALUControl = 5'b01001;
        #10;

        // Equal values -> result should be 0
        A = 32'h00000009; B = 32'h00000009; ALUControl = 5'b01001;
        #10;

        // Negative less-than case based on subtraction sign bit
        A = 32'hFFFFFFFE; B = 32'h00000001; ALUControl = 5'b01001;
        #10;

        // =========================================================
        // Arithmetic operation tests
        // ALUControl[1:0] = 10
        // ALUControl[3]   = 0 for ADD, 1 for SUB
        // =========================================================

        // ADD: 5 + 7 = 12
        A = 32'h00000005; B = 32'h00000007; ALUControl = 5'b00010;
        #10;

        // ADD: 0 + 0 = 0
        A = 32'h00000000; B = 32'h00000000; ALUControl = 5'b00010;
        #10;

        // ADD: negative + positive
        A = 32'hFFFFFFFC; B = 32'h00000002; ALUControl = 5'b00010;
        #10;

        // SUB: 9 - 4 = 5
        A = 32'h00000009; B = 32'h00000004; ALUControl = 5'b01010;
        #10;

        // SUB: 4 - 9 = negative result
        A = 32'h00000004; B = 32'h00000009; ALUControl = 5'b01010;
        #10;

        // SUB: equal values -> 0
        A = 32'h0000000A; B = 32'h0000000A; ALUControl = 5'b01010;
        #10;

        // =========================================================
        // Logic operation tests
        // ALUControl[1:0] = 11
        // ALUControl[2]   = 0 for AND, 1 for OR
        // =========================================================

        // AND
        A = 32'hF0F0F0F0; B = 32'h0FF00FF0; ALUControl = 5'b00011;
        #10;

        // AND with zero
        A = 32'h12345678; B = 32'h00000000; ALUControl = 5'b00011;
        #10;

        // AND all ones
        A = 32'hFFFFFFFF; B = 32'hAAAAAAAA; ALUControl = 5'b00011;
        #10;

        // OR
        A = 32'hF0F0F0F0; B = 32'h0FF00FF0; ALUControl = 5'b00111;
        #10;

        // OR with zero
        A = 32'h12345678; B = 32'h00000000; ALUControl = 5'b00111;
        #10;

        // OR mixed pattern
        A = 32'h55555555; B = 32'hAAAAAAAA; ALUControl = 5'b00111;
        #10;

        $finish;
    end

endmodule

SVcode/alu/alu_tb.vcd
$date
	Sun Mar 29 06:03:59 2026
$end
$version
	Icarus Verilog
$end
$timescale
	1ps
$end
$scope module alu_tb $end
$var wire 1 ! Zero $end
$var wire 32 " ALUResult [31:0] $end
$var reg 32 # A [31:0] $end
$var reg 5 $ ALUControl [4:0] $end
$var reg 32 % B [31:0] $end
$scope module dut $end
$var wire 32 & A [31:0] $end
$var wire 5 ' ALUControl [4:0] $end
$var wire 32 ( B [31:0] $end
$var wire 1 ! Zero $end
$var reg 32 ) ALUResult [31:0] $end
$var reg 32 * arith_result [31:0] $end
$var reg 32 + logic_result [31:0] $end
$var reg 32 , shift_result [31:0] $end
$var reg 32 - slt_result [31:0] $end
$upscope $end
$upscope $end
$enddefinitions $end
#0
$dumpvars
b1 -
b100 ,
b0 +
b11 *
b100 )
b10 (
b0 '
b1 &
b10 %
b0 $
b1 #
b100 "
0!
$end
#10000
b110000 "
b110000 )
b111 *
b110000 ,
b100 %
b100 (
b11 #
b11 &
#20000
b10010001101000101011001111000 "
b10010001101000101011001111000 )
b0 -
b10010001101000101011001111000 *
b10010001101000101011001111000 ,
b0 %
b0 (
b10010001101000101011001111000 #
b10010001101000101011001111000 &
#30000
b100 "
b100 )
b10010 *
b100 ,
b10000 $
b10000 '
b10 %
b10 (
b10000 #
b10000 &
#40000
b1000000000000000000000000000 "
b1000000000000000000000000000 )
b1 -
b10000000000000000000000000000100 *
b1000000000000000000000000000 ,
b100 %
b100 (
b10000000000000000000000000000000 #
b10000000000000000000000000000000 &
#50000
b10000111011001010100001100100001 "
b10000111011001010100001100100001 )
b10000111011001010100001100100001 *
b10000111011001010100001100100001 ,
b0 %
b0 (
b10000111011001010100001100100001 #
b10000111011001010100001100100001 &
#60000
b1 "
b1 )
b1 +
b11111111111111111111111111111110 *
b1100000 ,
b1001 $
b1001 '
b101 %
b101 (
b11 #
b11 &
#70000
1!
b0 "
b0 )
b0 -
b10 +
b101 *
b11100 ,
b10 %
b10 (
b111 #
b111 &
#80000
b1001 +
b0 *
b1001000000000 ,
b1001 %
b1001 (
b1001 #
b1001 &
#90000
0!
b1 "
b1 )
b1 -
b0 +
b11111111111111111111111111111101 *
b11111111111111111111111111111100 ,
b1 %
b1 (
b11111111111111111111111111111110 #
b11111111111111111111111111111110 &
#100000
b1100 "
b1100 )
b101 +
b1100 *
b1010000000 ,
b10 $
b10 '
b111 %
b111 (
b101 #
b101 &
#110000
1!
b0 "
b0 )
b0 -
b0 +
b0 *
b0 ,
b0 %
b0 (
b0 #
b0 &
#120000
0!
b11111111111111111111111111111110 "
b11111111111111111111111111111110 )
b1 -
b11111111111111111111111111111110 *
b11111111111111111111111111110000 ,
b10 %
b10 (
b11111111111111111111111111111100 #
b11111111111111111111111111111100 &
#130000
b101 "
b101 )
b0 -
b101 *
b10010000 ,
b1010 $
b1010 '
b100 %
b100 (
b1001 #
b1001 &
#140000
b11111111111111111111111111111011 "
b11111111111111111111111111111011 )
b1 -
b11111111111111111111111111111011 *
b100000000000 ,
b1001 %
b1001 (
b100 #
b100 &
#150000
1!
b0 "
b0 )
b0 -
b1010 +
b0 *
b10100000000000 ,
b1010 %
b1010 (
b1010 #
b1010 &
#160000
0!
b111100000000000011110000 "
b111100000000000011110000 )
b1 -
b111100000000000011110000 +
b111000010000000011100000 *
b11110000111100000000000000000000 ,
b11 $
b11 '
b1111111100000000111111110000 %
b1111111100000000111111110000 (
b11110000111100001111000011110000 #
b11110000111100001111000011110000 &
#170000
1!
b0 "
b0 )
b0 -
b0 +
b10010001101000101011001111000 *
b10010001101000101011001111000 ,
b0 %
b0 (
b10010001101000101011001111000 #
b10010001101000101011001111000 &
#180000
0!
b10101010101010101010101010101010 "
b10101010101010101010101010101010 )
b10101010101010101010101010101010 +
b10101010101010101010101010101001 *
b11111111111111111111110000000000 ,
b10101010101010101010101010101010 %
b10101010101010101010101010101010 (
b11111111111111111111111111111111 #
b11111111111111111111111111111111 &
#190000
b11111111111100001111111111110000 "
b11111111111100001111111111110000 )
b1 -
b11111111111100001111111111110000 +
b111000010000000011100000 *
b11110000111100000000000000000000 ,
b111 $
b111 '
b1111111100000000111111110000 %
b1111111100000000111111110000 (
b11110000111100001111000011110000 #
b11110000111100001111000011110000 &
#200000
b10010001101000101011001111000 "
b10010001101000101011001111000 )
b0 -
b10010001101000101011001111000 +
b10010001101000101011001111000 *
b10010001101000101011001111000 ,
b0 %
b0 (
b10010001101000101011001111000 #
b10010001101000101011001111000 &
#210000
b11111111111111111111111111111111 "
b11111111111111111111111111111111 )
b11111111111111111111111111111111 +
b11111111111111111111111111111111 *
b1010101010101010101010000000000 ,
b10101010101010101010101010101010 %
b10101010101010101010101010101010 (
b1010101010101010101010101010101 #
b1010101010101010101010101010101 &
